main.py
StreamDock/DeviceManager.py
StreamDock/ProductIDs.py
StreamDock/__init__.py
StreamDock/Devices/StreamDock.py
StreamDock/Devices/StreamDock293.py
StreamDock/Devices/__init__.py
StreamDock/ImageHelpers/PILHelper.py
StreamDock/ImageHelpers/__init__.py
StreamDock/Transport/LibUSBHIDAPI.py
StreamDock/Transport/__init__.py
StreamDock/Transport/libtransport.so
StreamDock/Transport/libtransport_arm64.so
streamdock-0.1.2.dist-info/LICENSE
streamdock-0.1.2.dist-info/METADATA
streamdock-0.1.2.dist-info/WHEEL
streamdock-0.1.2.dist-info/top_level.txt
streamdock-0.1.2.dist-info/RECORD
