Metadata-Version: 2.1
Name: streamdock
Version: 0.1.2
Summary: A Python package to control streamdock device at https://bbs.key123.vip
Author-email: Hugo Zhu <hugozhu@gmail.com>
License: MIT
Requires-Python: >=3.10.0
License-File: LICENSE
Requires-Dist: pyudev
Requires-Dist: pillow
